{
  "tenant_id": "system",
  "node_id": "cli_executor:v1.0.0",
  "node_name": "cli_executor",
  "version": "1.0.0",
  "name": "CLI Executor",
  "type": "cli_node",
  "description": "Execute shell commands safely",
  "config": {
    "command": "echo hello from cli_executor graphweave",
    "output_key": "cli_executor"
  },
  "input_contract": {
    "required": [
      {
        "name": "command",
        "type": "string",
        "description": "Bash command to execute",
        "state_path": "$.cli_executor.command"
      }
    ],
    "optional": []
  },
  "output_contract": {
    "produced": [
      {
        "name": "stdout",
        "type": "string",
        "description": "Captured standard output",
        "state_path": "$.cli_executor.stdout"
      },
      {
        "name": "stderr",
        "type": "string",
        "description": "Captured standard error",
        "state_path": "$.cli_executor.stderr"
      },
      {
        "name": "exit_code",
        "type": "number",
        "description": "Process exit code",
        "state_path": "$.cli_executor.exit_code"
      }
    ]
  },
  "tags": ["automation", "cli"],
  "owner": "system",
  "status": "active"
}
